lpip/__init__.py
lpip/__main__.py
lpip-1.0.7.dist-info/LICENSE
lpip-1.0.7.dist-info/METADATA
lpip-1.0.7.dist-info/WHEEL
lpip-1.0.7.dist-info/entry_points.txt
lpip-1.0.7.dist-info/top_level.txt
lpip-1.0.7.dist-info/RECORD
