Metadata-Version: 2.1
Name: lpip
Version: 1.0.7
Summary: Offline package manager for Python
Home-page: https://github.com/alexbourg/LocalPIP
Author: Alex BOURG
Author-email: alex.bourg@outlook.com
License: MIT
Keywords: localpip,lpip,python,offline,package manager,anaconda
Platform: UNKNOWN
Classifier: License :: OSI Approved :: MIT License
Classifier: Programming Language :: Python :: 3
Classifier: Programming Language :: Python :: 3.8
Classifier: Programming Language :: Python :: 3.9
Classifier: Operating System :: Microsoft :: Windows
License-File: LICENSE
Requires-Dist: requests
Requires-Dist: bs4
Requires-Dist: pypac
